exflibrary/__init__.py
exflibrary/my_module.py
exflibrary-1.11.dist-info/METADATA
exflibrary-1.11.dist-info/WHEEL
exflibrary-1.11.dist-info/top_level.txt
exflibrary-1.11.dist-info/RECORD
