Metadata-Version: 2.1
Name: exflibrary
Version: 1.11
Summary: Library for malware building, educational purposes only
Home-page: https://github.com/miracledevelop/exflibrary
Author: Adam Johns
Author-email: rusty128944@gmail.com
Classifier: Programming Language :: Python :: 3
Classifier: License :: OSI Approved :: MIT License
Classifier: Operating System :: OS Independent
Requires-Python: >=3.6
Requires-Dist: requests
